knocki/__init__.py
knocki/exceptions.py
knocki/knocki.py
knocki/models.py
knocki/py.typed
knocki-0.4.1.dist-info/LICENSE.md
knocki-0.4.1.dist-info/METADATA
knocki-0.4.1.dist-info/WHEEL
knocki-0.4.1.dist-info/RECORD
